pydrift/__init__.py
pydrift/constants.py
pydrift/core/drift_checker.py
pydrift/core/drift_checker_estimator.py
pydrift/core/interpretable_drift.py
pydrift/decorators.py
pydrift/exceptions.py
pydrift/models.py
pydrift/test/__init__.py
pydrift/test/test_drift_checker.py
pydrift-0.2.15.dist-info/LICENSE
pydrift-0.2.15.dist-info/WHEEL
pydrift-0.2.15.dist-info/METADATA
pydrift-0.2.15.dist-info/RECORD
