Metadata-Version: 2.1
Name: pydrift
Version: 0.2.15
Summary: How do we measure the degradation of a machine learning process? Why does the performance of our predictive models decrease? Maybe it is that a data source has changed (one or more variables) or maybe what changes is the relationship of these variables with the target we want to predict. `pydrift` tries to facilitate this task to the data scientist, performing this kind of checks and somehow measuring that degradation.
Home-page: https://github.com/sergiocalde94/pydrift
License: MIT
Author: sergiocalde94
Author-email: sergiocalde94@gmail.com
Requires-Python: >=3.6.1
Classifier: License :: OSI Approved :: MIT License
Classifier: Programming Language :: Python :: 3
Classifier: Programming Language :: Python :: 3.7
Provides-Extra: plotting
Requires-Dist: catboost (>=0.23)
Requires-Dist: llvmlite (>0.33.0)
Requires-Dist: numba (>=0.51.2)
Requires-Dist: pandas (>=1.0.3)
Requires-Dist: plotly (>=4.8.1); extra == "plotting"
Requires-Dist: scikit-learn (>=0.23.1)
Requires-Dist: shap (>=0.35.0)
Requires-Dist: statsmodels (>=0.11.1)
Requires-Dist: typing-extensions (>=3.7.4); python_version < "3.8"
Project-URL: Documentation, https://sergiocalde94.github.io/pydrift/
Project-URL: Repository, https://github.com/sergiocalde94/pydrift
